<?xml version="1.0" encoding="UTF-8" standalone="no"?><botica.xml><Clientes><Cliente><dni>77812475W</dni><nombre>Daniel Diaz</nombre><direccion>Calle 1</direccion><telefono>652228921</telefono><baja>true</baja></Cliente><Cliente><dni>12345678Z</dni><nombre>Elisabeth Olsen</nombre><direccion>Mulholland Drive 10</direccion><telefono>623456789</telefono><baja>false</baja></Cliente></Clientes><Productos><Medicamento><codigo>1234567898765</codigo><nombre>Med 1</nombre><descripcion>Mi medicamento 01</descripcion><precio>2.59</precio><unidades>200</unidades><tipoMedicamento>LAXANTES</tipoMedicamento><comoTomar>Oral</comoTomar><efectosAdversos>Muchos</efectosAdversos></Medicamento><ParaFarmacia><codigo>4444444444444</codigo><nombre>Par 1</nombre><descripcion>Mi parafarmacia 02</descripcion><precio>12.5</precio><unidades>100</unidades><categoria>NASAL</categoria><dosisUnidades>15</dosisUnidades><descuento>5.0</descuento></ParaFarmacia></Productos></botica.xml>